drylab_tools_sdk/__init__.py
drylab_tools_sdk/_http.py
drylab_tools_sdk/_version.py
drylab_tools_sdk/client.py
drylab_tools_sdk/exceptions.py
drylab_tools_sdk/auth/__init__.py
drylab_tools_sdk/auth/token.py
drylab_tools_sdk/models/__init__.py
drylab_tools_sdk/models/job.py
drylab_tools_sdk/models/pipeline.py
drylab_tools_sdk/models/pokemon.py
drylab_tools_sdk/models/vault.py
drylab_tools_sdk/resources/__init__.py
drylab_tools_sdk/resources/base.py
drylab_tools_sdk/resources/jobs.py
drylab_tools_sdk/resources/pipelines.py
drylab_tools_sdk/resources/pokemon.py
drylab_tools_sdk/resources/vault.py
drylab_tools_sdk-0.4.dist-info/METADATA
drylab_tools_sdk-0.4.dist-info/WHEEL
drylab_tools_sdk-0.4.dist-info/RECORD
