Metadata-Version: 2.4
Name: drylab-tools-sdk
Version: 0.4
Summary: Python SDK for Drylab Backend API - vault, jobs, and pipelines
Project-URL: Homepage, https://thedrylab.com
Project-URL: Documentation, https://docs.thedrylab.com
Project-URL: Repository, https://github.com/Drylab-AI/drylab-tools-sdk
Author-email: Drylab <hoangphan@thedrylab.com>
License-Expression: MIT
Keywords: api,bioinformatics,drylab,nextflow,sdk
Classifier: Development Status :: 4 - Beta
Classifier: Intended Audience :: Developers
Classifier: Intended Audience :: Science/Research
Classifier: License :: OSI Approved :: MIT License
Classifier: Programming Language :: Python :: 3
Classifier: Programming Language :: Python :: 3.9
Classifier: Programming Language :: Python :: 3.10
Classifier: Programming Language :: Python :: 3.11
Classifier: Programming Language :: Python :: 3.12
Classifier: Topic :: Scientific/Engineering :: Bio-Informatics
Requires-Python: >=3.9
Requires-Dist: requests>=2.28.0
Provides-Extra: dev
Requires-Dist: black>=23.0.0; extra == 'dev'
Requires-Dist: mypy>=1.0.0; extra == 'dev'
Requires-Dist: pytest-cov>=4.0.0; extra == 'dev'
Requires-Dist: pytest>=7.0.0; extra == 'dev'
Requires-Dist: responses>=0.23.0; extra == 'dev'
Requires-Dist: ruff>=0.1.0; extra == 'dev'
